sfx/__about__.py
sfx/__init__.py
sfx/main.py
sfx/basis/__init__.py
sfx/basis/basis/__init__.py
sfx/basis/basis/_basis.py
sfx/basis/functions/__init__.py
sfx/basis/functions/matrix/__init__.py
sfx/basis/functions/matrix/mobilities/__init__.py
sfx/basis/functions/matrix/mobilities/_mobilities.py
sfx/basis/functions/scalar/__init__.py
sfx/basis/functions/scalar/potentials/__init__.py
sfx/basis/functions/scalar/potentials/_potentials.py
sfx/basis/functions/vector/__init__.py
sfx/basis/functions/vector/forces/__init__.py
sfx/basis/functions/vector/forces/_forces.py
sfx/basis/interactions/__init__.py
sfx/basis/interactions/_interactions.py
sfx/basis/kernels/__init__.py
sfx/basis/kernels/one_body/__init__.py
sfx/basis/kernels/one_body/_one_body.py
sfx/basis/kernels/two_body/__init__.py
sfx/basis/kernels/two_body/_two_body.py
sfx/basis/parameters/__init__.py
sfx/basis/parameters/_parameters.py
sfx/core/__init__.py
sfx/core/_hickle_loaders/__init__.py
sfx/core/_hickle_loaders/_load_jax.py
sfx/core/sfx_object/__init__.py
sfx/core/sfx_object/_sfx_object.py
sfx/helpers/__init__.py
sfx/helpers/analysis/__init__.py
sfx/helpers/analysis/_analysis.py
sfx/helpers/batch/__init__.py
sfx/helpers/batch/_batch.py
sfx/helpers/format/__init__.py
sfx/helpers/format/_format.py
sfx/helpers/inference/__init__.py
sfx/helpers/inference/_inference.py
sfx/helpers/io/__init__.py
sfx/helpers/io/_io.py
sfx/helpers/math/__init__.py
sfx/helpers/math/_math.py
sfx/helpers/optimize/__init__.py
sfx/helpers/optimize/_optimize.py
sfx/helpers/sharding/__init__.py
sfx/helpers/sharding/_sharding.py
sfx/helpers/simulation/__init__.py
sfx/helpers/simulation/_simulation.py
sfx/helpers/utils/__init__.py
sfx/helpers/utils/_utils.py
sfx/helpers/visualization/exr/__init__.py
sfx/helpers/visualization/exr/_exr.py
sfx/helpers/visualization/gltf/__init__.py
sfx/helpers/visualization/gltf/_gltf.py
sfx/inference/__init__.py
sfx/inference/data/__init__.py
sfx/inference/data/_data.py
sfx/inference/estimators/__init__.py
sfx-0.1.0.dist-info/licenses/LICENSE
sfx-0.1.0.dist-info/METADATA
sfx-0.1.0.dist-info/WHEEL
sfx-0.1.0.dist-info/top_level.txt
sfx-0.1.0.dist-info/RECORD
